ytplpy/__init__.py
ytplpy/main.py
ytplpy-0.0.1.dist-info/LICENCE
ytplpy-0.0.1.dist-info/METADATA
ytplpy-0.0.1.dist-info/WHEEL
ytplpy-0.0.1.dist-info/top_level.txt
ytplpy-0.0.1.dist-info/RECORD
