Metadata-Version: 2.1
Name: ytplpy
Version: 0.0.1
Summary: UNKNOWN
Home-page: https://github.com/suave101
Author: Rico Suave
License: UNKNOWN
Platform: UNKNOWN
Classifier: Programming Language :: Python :: 3
Classifier: License :: OSI Approved :: MIT License
Classifier: Operating System :: OS Independent
Requires-Python: >=3.6
Requires-Dist: pytube
Requires-Dist: moviepy
